visual/__init__.py
visual/visual.py
visual/examples/__init__.py
visual/examples/fractal/__init__.py
visual/examples/fractal/example_fractal.py
visual/examples/fractal/fractal.py
visual/examples/functions/example_alpha_layer.py
visual/examples/functions/example_arrows.py
visual/examples/functions/example_bezier_curve.py
visual/examples/functions/example_cercle.py
visual/examples/functions/example_croix.py
visual/examples/functions/example_droite.py
visual/examples/functions/example_findwithpoint.py
visual/examples/functions/example_interpolation.py
visual/examples/functions/example_lines.py
visual/examples/functions/example_plot.py
visual/examples/functions/example_point.py
visual/examples/functions/example_polygone.py
visual/examples/functions/example_rectangle.py
visual/examples/functions/example_rotate.py
visual/examples/functions/example_scatter.py
visual/examples/functions/example_triangle.py
visual/examples/functions/example_vectoriel_geometry.py
visual/examples/functions/example_vectors.py
visual/examples/introduction/example.py
visual/extensions/__init__.py
visual/extensions/ellipses/__init__.py
visual/extensions/ellipses/ellipses_example.py
visual/extensions/ellipses/ext_ellipses.py
visual/extensions/grapher/__init__.py
visual/extensions/grapher/ext_grapher.py
visual/extensions/lines/__init__.py
visual/extensions/lines/ext_lines.py
visual/extensions/lines/lines_example.py
visual/extensions/turtle/__init__.py
visual/extensions/turtle/ext_turtle.py
visual/extensions/turtle/ext_turtle_for_computer.py
visual/extensions/turtle/turtle_example.py
visualcore-1.0.2.dist-info/licenses/LICENCE.md
visualcore-1.0.2.dist-info/METADATA
visualcore-1.0.2.dist-info/WHEEL
visualcore-1.0.2.dist-info/entry_points.txt
visualcore-1.0.2.dist-info/top_level.txt
visualcore-1.0.2.dist-info/RECORD
