Metadata-Version: 2.4
Name: visualcore
Version: 1.0.2
Summary: A graphical and compact library for the Numworks calculator and its emulator
Author-email: Archange <archange_paradise@proton.me>
License: MIT
Project-URL: Homepage, https://github.com/Archange-py/Visual
Project-URL: Repository, https://github.com/Archange-py/Visual
Project-URL: Numworks, https://my.numworks.com/python/archange/visual
Project-URL: Library, https://pypi.org/project/visualcore/
Keywords: visual,Numworks,algorithm,calculator,python
Classifier: Programming Language :: Python :: 3
Classifier: License :: OSI Approved :: MIT License
Classifier: Operating System :: OS Independent
Requires-Python: >=3.9
License-File: LICENCE.md
Requires-Dist: kandinsky==2.7.2
Requires-Dist: ion-numworks==2.1
Provides-Extra: dev
Requires-Dist: pytest; extra == "dev"
Dynamic: license-file
